fbchat/__init__.py
fbchat/_attachment.py
fbchat/_client.py
fbchat/_core.py
fbchat/_exception.py
fbchat/_file.py
fbchat/_graphql.py
fbchat/_group.py
fbchat/_location.py
fbchat/_message.py
fbchat/_mqtt.py
fbchat/_page.py
fbchat/_plan.py
fbchat/_poll.py
fbchat/_quick_reply.py
fbchat/_state.py
fbchat/_sticker.py
fbchat/_thread.py
fbchat/_user.py
fbchat/_util.py
fbchat/models.py
fbchat_clone-0.0.1.dist-info/METADATA
fbchat_clone-0.0.1.dist-info/WHEEL
fbchat_clone-0.0.1.dist-info/top_level.txt
fbchat_clone-0.0.1.dist-info/RECORD
